{
  "title": "Prthvi Tvaya Dhrita Loka",
  "audioStream": "",
  "audioName": "",
  "contentBlocks": [
    {
      "stanzaNumber": 1,
      "original": "ॐ पृथ्वि त्वया धृता लोका\nदेवि त्वं विष्णुना धृता ।\nत्वं च धारय मां देवि\nपवित्रं कुरु चासनम् ॥",
      "transliteration": "ŏm Prthvi ṭvayaa ḍhrtaa l̤okaa\nḍevi ṭvam Vissnnunaa ḍhrtaa |\nṭvam Ca ḍhaaraya ṃaam ḍevi\nPavitram ḵuru Ca-[ā]asanam ||",
      "translation": "Om, O Prithivi devi, by you are borne the entire loka (world); and devi, you in turn are borne by Sri Vishnu, please hold me (on your lap), and make this asana (seat of the worshipper) pure.",
      "meanings": "ॐ (om) – sacred sound; पृथ्वि (pṛthvi) – earth; त्वया (tvayā) – by you; धृता (dhṛtā) – borne; लोका (lokāḥ) – worlds; देवि (devi) – goddess; त्वं (tvaṃ) – you; विष्णुना (viṣṇunā) – by Vishnu; धृता (dhṛtā) – borne; त्वं (tvaṃ) – you; च (ca) – and; धारय (dhāraya) – hold; मां (māṃ) – me; देवि (devi) – goddess; पवित्रं (pavitraṃ) – pure; कुरु (kuru) – make; चासनम् (cāsanam) – and seat (ca:and | āsanam:seat);"
    }
  ]
}